plotickz/__init__.py
plotickz/api.py
plotickz/core.py
plotickz/utils.py
plotickz-0.1.1.dist-info/METADATA
plotickz-0.1.1.dist-info/WHEEL
plotickz-0.1.1.dist-info/top_level.txt
plotickz-0.1.1.dist-info/RECORD
