Metadata-Version: 2.4
Name: plotickz
Version: 0.1.1
Summary: Add your description here
Requires-Python: >=3.10
Requires-Dist: numpy>=2.2.6
